pypmanager/__init__.py
pypmanager/__main__.py
pypmanager/const.py
pypmanager/error.py
pypmanager/settings.py
pypmanager/analytics/__init__.py
pypmanager/analytics/holding.py
pypmanager/analytics/portfolio.py
pypmanager/analytics/security.py
pypmanager/helpers/__init__.py
pypmanager/loader_market_data/__init__.py
pypmanager/loader_market_data/avanza.py
pypmanager/loader_market_data/base_loader.py
pypmanager/loader_market_data/const.py
pypmanager/loader_market_data/ft.py
pypmanager/loader_market_data/models.py
pypmanager/loader_market_data/morningstar.py
pypmanager/loader_market_data/utils.py
pypmanager/loader_transaction/__init__.py
pypmanager/loader_transaction/avanza.py
pypmanager/loader_transaction/base_loader.py
pypmanager/loader_transaction/calculate_aggregates.py
pypmanager/loader_transaction/const.py
pypmanager/loader_transaction/general_ledger.py
pypmanager/loader_transaction/lysa.py
pypmanager/loader_transaction/misc.py
pypmanager/server/__init__.py
pypmanager/server/const.py
pypmanager/server/templates.py
pypmanager/server/graphql/__init__.py
pypmanager/server/graphql/models.py
pypmanager/server/graphql/query.py
pypmanager/utils/__init__.py
pypmanager/utils/dt.py
script/__init__.py
pylocalpmanager-2023.12.2.dist-info/METADATA
pylocalpmanager-2023.12.2.dist-info/WHEEL
pylocalpmanager-2023.12.2.dist-info/top_level.txt
pylocalpmanager-2023.12.2.dist-info/RECORD
