Metadata-Version: 2.1
Name: pylocalpmanager
Version: 2023.12.2
Platform: any
Requires-Python: >=3.11
Requires-Dist: colorlog ==6.8.0
Requires-Dist: fastapi ==0.105.0
Requires-Dist: humanize ==4.9.0
Requires-Dist: Jinja2 ==3.1.2
Requires-Dist: lxml ==4.9.4
Requires-Dist: pandas ==2.1.4
Requires-Dist: pydantic-settings ==2.1.0
Requires-Dist: requests ==2.31.0
Requires-Dist: strawberry-graphql[debug-server] ==0.217.0
Requires-Dist: uvicorn[standard] ==0.25.0
Provides-Extra: test
Requires-Dist: black ==23.12.1 ; extra == 'test'
Requires-Dist: httpx ==0.26.0 ; extra == 'test'
Requires-Dist: mypy ==1.8.0 ; extra == 'test'
Requires-Dist: pre-commit ==3.6.0 ; extra == 'test'
Requires-Dist: pylint ==3.0.3 ; extra == 'test'
Requires-Dist: pytest ==7.4.3 ; extra == 'test'
Requires-Dist: pytest-asyncio ==0.23.2 ; extra == 'test'
Requires-Dist: pytest-cov ==4.1.0 ; extra == 'test'
Requires-Dist: pytest-timeout ==2.2.0 ; extra == 'test'
Requires-Dist: types-PyYAML ==6.0.12.12 ; extra == 'test'
Requires-Dist: types-requests ==2.31.0.10 ; extra == 'test'
